fs/proxy/__init__.py
fs/proxy/_utils.py
fs/proxy/base.py
fs/proxy/writer.py
fs.proxy-0.1.4.dist-info/DESCRIPTION.rst
fs.proxy-0.1.4.dist-info/METADATA
fs.proxy-0.1.4.dist-info/RECORD
fs.proxy-0.1.4.dist-info/WHEEL
fs.proxy-0.1.4.dist-info/metadata.json
fs.proxy-0.1.4.dist-info/top_level.txt
fs.proxy-0.1.4.dist-info/zip-safe
