Metadata-Version: 2.0
Name: fs.proxy
Version: 0.1.4
Summary: Miscellaneous proxy filesystems for Pyfilesystem2
Home-page: https://github.com/althonos/fs.proxy
Author: Martin Larralde
Author-email: martin.larralde@ens-cachan.fr
License: MIT
Keywords: proxy,filesystem,Pyfilesystem2
Platform: any
Classifier: Development Status :: 4 - Beta
Classifier: Intended Audience :: Developers
Classifier: License :: OSI Approved :: MIT License
Classifier: Operating System :: OS Independent
Classifier: Programming Language :: Python
Classifier: Programming Language :: Python :: 2.7
Classifier: Programming Language :: Python :: 3.3
Classifier: Programming Language :: Python :: 3.4
Classifier: Programming Language :: Python :: 3.5
Classifier: Programming Language :: Python :: 3.6
Classifier: Topic :: Software Development :: Libraries :: Python Modules
Classifier: Topic :: System :: Filesystems
Requires-Python: >= 2.7, != 3.0.*, != 3.1.*, != 3.2.*
Requires-Dist: fs (~=2.0.4)
Requires-Dist: six (~=1.10)
Requires-Dist: psutil (~=2.0)
